chaosk8s_wix/__init__.py
chaosk8s_wix/actions.py
chaosk8s_wix/probes.py
chaosk8s_wix/aws/__init__.py
chaosk8s_wix/aws/actions.py
chaosk8s_wix/aws/probes.py
chaosk8s_wix/consul/__init__.py
chaosk8s_wix/consul/actions.py
chaosk8s_wix/consul/probes.py
chaosk8s_wix/grafana/__init__.py
chaosk8s_wix/grafana/probes.py
chaosk8s_wix/node/__init__.py
chaosk8s_wix/node/actions.py
chaosk8s_wix/node/probes.py
chaosk8s_wix/pod/__init__.py
chaosk8s_wix/pod/actions.py
chaosk8s_wix/pod/probes.py
chaosk8s_wix/slack/__init__.py
chaosk8s_wix/slack/client.py
chaosk8s_wix/slack/logger_handler.py
chaostoolkit_k8s_wix-1.4.8.dist-info/LICENSE
chaostoolkit_k8s_wix-1.4.8.dist-info/METADATA
chaostoolkit_k8s_wix-1.4.8.dist-info/WHEEL
chaostoolkit_k8s_wix-1.4.8.dist-info/top_level.txt
chaostoolkit_k8s_wix-1.4.8.dist-info/RECORD
