Metadata-Version: 2.1
Name: chaostoolkit-k8s-wix
Version: 1.4.8
Summary: Extended version of Chaos Toolkit Kubernetes support
Home-page: http://chaostoolkit.org
Author: chaostoolkit Team
Author-email: contact@chaostoolkit.org
License: Apache License Version 2
Platform: UNKNOWN
Classifier: Development Status :: 2 - Pre-Alpha
Classifier: Intended Audience :: Developers
Classifier: License :: Freely Distributable
Classifier: Operating System :: OS Independent
Classifier: License :: OSI Approved :: Apache Software License
Classifier: Programming Language :: Python
Classifier: Programming Language :: Python :: 3
Classifier: Programming Language :: Python :: 3.5
Classifier: Programming Language :: Python :: 3.6
Classifier: Programming Language :: Python :: Implementation
Classifier: Programming Language :: Python :: Implementation :: CPython
Requires-Python: >=3.5.*
Requires-Dist: dateparser
Requires-Dist: kubernetes
Requires-Dist: logzero
Requires-Dist: chaostoolkit-lib (>=0.15.1)
Requires-Dist: pyyaml
Requires-Dist: slackclient (==1.3.0)
Requires-Dist: fabric3
Requires-Dist: boto3
Requires-Dist: python-consul
Requires-Dist: jinja2
